simulateur_trafic/__init__.py
simulateur_trafic/core/__init__.py
simulateur_trafic/core/analyseur.py
simulateur_trafic/core/simulateur.py
simulateur_trafic/data/config_reseau.json
simulateur_trafic/io/__init__.py
simulateur_trafic/io/affichage.py
simulateur_trafic/io/export.py
simulateur_trafic/models/__init__.py
simulateur_trafic/models/reseau.py
simulateur_trafic/models/route.py
simulateur_trafic/models/vehicule.py
simulateur_trafic/requirements.txt
simulateur_trafic/tests/conftest.py
simulateur_trafic/tests/test_reseau.py
simulateur_trafic/tests/test_route.py
simulateur_trafic/tests/test_simulateur.py
simulateur_trafic/tests/test_vehicule.py
simulateur_trafic_mahdiba11-0.1.0.dist-info/METADATA
simulateur_trafic_mahdiba11-0.1.0.dist-info/WHEEL
simulateur_trafic_mahdiba11-0.1.0.dist-info/RECORD
