Metadata-Version: 2.4
Name: simulateur_trafic_mahdiba11
Version: 0.1.0
Summary: simulator for traffic
License: Apache2.0
Author: mahdi_ben_ameur
Requires-Python: >=3.12
Classifier: License :: Other/Proprietary License
Classifier: Programming Language :: Python :: 3
Classifier: Programming Language :: Python :: 3.12
Classifier: Programming Language :: Python :: 3.13
Classifier: Programming Language :: Python :: 3.14
Requires-Dist: matplotlib (==3.10.0)
Requires-Dist: numpy (==1.26.4)
